strongarm/__init__.py
strongarm/debug_util.py
strongarm/cli/__init__.py
strongarm/cli/utils.py
strongarm/macho/__init__.py
strongarm/macho/arch_independent_structs.py
strongarm/macho/dyld_info_parser.py
strongarm/macho/dyld_shared_cache.py
strongarm/macho/macho_analyzer.py
strongarm/macho/macho_binary.py
strongarm/macho/macho_definitions.py
strongarm/macho/macho_imp_stubs.py
strongarm/macho/macho_load_commands.py
strongarm/macho/macho_parse.py
strongarm/macho/macho_string_table_helper.py
strongarm/macho/objc_runtime_data_parser.py
strongarm/macho/codesign/__init__.py
strongarm/macho/codesign/codesign_definitions.py
strongarm/macho/codesign/codesign_parser.py
strongarm/objc/__init__.py
strongarm/objc/objc_analyzer.py
strongarm/objc/objc_instruction.py
strongarm_ios-10.5.1.data/data/LICENSE.txt
strongarm_ios-10.5.1.dist-info/LICENSE.txt
strongarm_ios-10.5.1.dist-info/METADATA
strongarm_ios-10.5.1.dist-info/WHEEL
strongarm_ios-10.5.1.dist-info/top_level.txt
strongarm_ios-10.5.1.dist-info/RECORD
